ringkasan/__init__.py
ringkasan/core/core.py
ringkasan-0.1.2.dist-info/entry_points.txt
ringkasan-0.1.2.dist-info/LICENSE
ringkasan-0.1.2.dist-info/WHEEL
ringkasan-0.1.2.dist-info/METADATA
ringkasan-0.1.2.dist-info/RECORD
